pulumi_null/__init__.py
pulumi_null/_utilities.py
pulumi_null/get_data_source.py
pulumi_null/provider.py
pulumi_null/pulumi-plugin.json
pulumi_null/py.typed
pulumi_null/resource.py
pulumi_null-0.0.14.dist-info/METADATA
pulumi_null-0.0.14.dist-info/WHEEL
pulumi_null-0.0.14.dist-info/top_level.txt
pulumi_null-0.0.14.dist-info/RECORD
